telestream_cloud_stores/__init__.py
telestream_cloud_stores/api_client.py
telestream_cloud_stores/configuration.py
telestream_cloud_stores/rest.py
telestream_cloud_stores/api/__init__.py
telestream_cloud_stores/api/stores_api.py
telestream_cloud_stores/models/__init__.py
telestream_cloud_stores/models/alternative_path_format.py
telestream_cloud_stores/models/error.py
telestream_cloud_stores/models/error_response.py
telestream_cloud_stores/models/object_url.py
telestream_cloud_stores/models/output.py
telestream_cloud_stores/models/store.py
telestream_cloud_stores/models/store_body.py
telestream_cloud_stores/models/store_body_provider_specific_settings.py
telestream_cloud_stores/models/validate_bucket_body.py
telestream_cloud_stores/models/validate_bucket_response.py
telestream_cloud_stores/models/watch_rule.py
test/__init__.py
test/test_alternative_path_format.py
test/test_error.py
test/test_error_response.py
test/test_object_url.py
test/test_output.py
test/test_store.py
test/test_store_body.py
test/test_store_body_provider_specific_settings.py
test/test_stores_api.py
test/test_validate_bucket_body.py
test/test_validate_bucket_response.py
test/test_watch_rule.py
telestream_cloud_stores-2.0.0.dist-info/METADATA
telestream_cloud_stores-2.0.0.dist-info/WHEEL
telestream_cloud_stores-2.0.0.dist-info/top_level.txt
telestream_cloud_stores-2.0.0.dist-info/RECORD
