Metadata-Version: 2.1
Name: telestream-cloud-stores
Version: 2.0.0
Summary: API
Home-page: https://github.com/telestream/telestream-cloud-python-sdk
Author: UNKNOWN
Author-email: you@your-company.com
License: UNKNOWN
Keywords: Swagger,API
Platform: UNKNOWN
Requires-Dist: urllib3 (>=1.15)
Requires-Dist: six (>=1.10)
Requires-Dist: certifi
Requires-Dist: python-dateutil
Requires-Dist: requests
